bitalino_rs-0.1.13.dist-info/METADATA
bitalino_rs-0.1.13.dist-info/WHEEL
bitalino_rs-0.1.13.dist-info/entry_points.txt
bitalino_rs-0.1.13.dist-info/licenses/LICENSE
bitalino_rs/__init__.py
bitalino_rs/__init__.pyi
bitalino_rs/_bitalino_core.abi3.so
bitalino_rs/_bitalino_core.pyi
bitalino_rs/device.py
bitalino_rs/device.pyi
bitalino_rs/logging.py
bitalino_rs/logging.pyi
bitalino_rs/models.py
bitalino_rs/models.pyi
bitalino_rs/py.typed
bitalino_rs-0.1.13.dist-info/RECORD
