Metadata-Version: 2.4
Name: bitalino-rs
Version: 0.1.13
License-File: LICENSE
License-File: LICENSE
Summary: BITalino Bluetooth/serial driver with Python bindings (PyO3, abi3).
Home-Page: https://github.com/tleygue/bitalino_rs
Author-email: tleygue <36546314+tleygue@users.noreply.github.com>
Requires-Python: >=3.11
